sydneysuburbs/__init__.py
sydneysuburbs/generators.py
sydneysuburbs/suburb.py
sydneysuburbs/suburb_game.py
sydneysuburbs/suburb_network.py
sydneysuburbs/data/__init__.py
sydneysuburbs/data/inner-west.geojson
sydneysuburbs/data/test.geojson
sydneysuburbs-0.1.1.dist-info/METADATA
sydneysuburbs-0.1.1.dist-info/WHEEL
sydneysuburbs-0.1.1.dist-info/licenses/LICENSE
sydneysuburbs-0.1.1.dist-info/RECORD
